README.rst
setup.py
turtlestar.py
turtlestar.egg-info/PKG-INFO
turtlestar.egg-info/SOURCES.txt
turtlestar.egg-info/dependency_links.txt
turtlestar.egg-info/top_level.txt