Metadata-Version: 1.1
Name: turtlestar
Version: 1.0.2
Summary: 使用turtle模块画出星空的程序。A program uses module turtle to draw stars.
Home-page: UNKNOWN
Author: 七分诚意 qq:3076711200 邮箱:3416445406@qq.com
Author-email: 3416445406@qq.com
License: UNKNOWN
Keywords: turtle,star,turtlestar,graphics
Platform: UNKNOWN
Classifier: Programming Language :: Python
Classifier: Natural Language :: Chinese (Simplified)
Classifier: Topic :: Multimedia :: Graphics
